alias/__init__.py
alias/alias.py
alias/group.py
alias/vehicle.py
alias/__pycache__/__init__.cpython-37.pyc
alias/__pycache__/alias.cpython-37.pyc
alias/__pycache__/vehicle.cpython-37.pyc
alias/drivers/__init__.py
alias/drivers/__init__.pyc
alias/drivers/alpaca.py
alias/drivers/alpacabasic.py
alias/drivers/blockchaincom.py
alias/drivers/cache.py
alias/drivers/cypherwrap.py
alias/drivers/drivers.py
alias/drivers/etherchainorg.py
alias/drivers/etherscan.py
alias/drivers/oanda.py
alias/drivers/robinhood.py
alias/drivers/xbitcoin.py
alias/drivers/__pycache__/__init__.cpython-37.pyc
alias/drivers/__pycache__/alpaca.cpython-37.pyc
alias/drivers/__pycache__/cache.cpython-37.pyc
alias/drivers/__pycache__/drivers.cpython-37.pyc
alias/drivers/__pycache__/oanda.cpython-37.pyc
alias/sockets/bitfinex_socket.py
alias/sockets/kraken_connection.py
alias/util/colors.py
alias/util/format.py
alias/util/symbols.py
alias/util/xtime.py
alias/util/__pycache__/format.cpython-37.pyc
alias/util/__pycache__/symbols.cpython-37.pyc
alias/util/__pycache__/xtime.cpython-37.pyc
alias-0.3.10.dist-info/METADATA
alias-0.3.10.dist-info/WHEEL
alias-0.3.10.dist-info/top_level.txt
alias-0.3.10.dist-info/RECORD
