Metadata-Version: 2.1
Name: alias
Version: 0.3.10
Summary: Alias is the container.
Home-page: https://github.com/psytron/alias
Author: Mico Malecki
Author-email: m@psytron.com
License: PSYTRON
Platform: UNKNOWN
Requires-Dist: keycache
Requires-Dist: pandas
Requires-Dist: alpaca-trade-api
Requires-Dist: v20
Requires-Dist: ccxt
